cjm_fasthtml_workflows/__init__.py
cjm_fasthtml_workflows/_modidx.py
cjm_fasthtml_workflows/core/__init__.py
cjm_fasthtml_workflows/core/deduplication.py
cjm_fasthtml_workflows/core/helpers.py
cjm_fasthtml_workflows/core/job_session.py
cjm_fasthtml_workflows/core/workflow_session.py
cjm_fasthtml_workflows-0.0.1.dist-info/licenses/LICENSE
cjm_fasthtml_workflows-0.0.1.dist-info/METADATA
cjm_fasthtml_workflows-0.0.1.dist-info/WHEEL
cjm_fasthtml_workflows-0.0.1.dist-info/entry_points.txt
cjm_fasthtml_workflows-0.0.1.dist-info/top_level.txt
cjm_fasthtml_workflows-0.0.1.dist-info/RECORD
