Metadata-Version: 2.4
Name: cjm-fasthtml-workflows
Version: 0.0.1
Summary: Session-based workflow management for FastHTML applications with multi-step state tracking, job metadata storage, and operation deduplication.
Home-page: https://github.com/cj-mills/cjm-fasthtml-workflows
Author: Christian J. Mills
Author-email: 9126128+cj-mills@users.noreply.github.com
License: Apache Software License 2.0
Keywords: nbdev jupyter notebook python
Classifier: Development Status :: 4 - Beta
Classifier: Intended Audience :: Developers
Classifier: Natural Language :: English
Classifier: Programming Language :: Python :: 3.11
Classifier: Programming Language :: Python :: 3.12
Classifier: License :: OSI Approved :: Apache Software License
Requires-Python: >=3.11
License-File: LICENSE
Provides-Extra: dev
Dynamic: author
Dynamic: author-email
Dynamic: classifier
Dynamic: description
Dynamic: description-content-type
Dynamic: home-page
Dynamic: keywords
Dynamic: license
Dynamic: license-file
Dynamic: provides-extra
Dynamic: requires-python
Dynamic: summary
